adaptiveagatepy/__init__.py
adaptiveagatepy/azure_token_provider.py
adaptiveagatepy/config.py
adaptiveagatepy/db.py
adaptiveagatepy/file.py
adaptiveagatepy/file_cache.py
adaptiveagatepy/item.py
adaptiveagatepy/item_cache.py
adaptiveagatepy/project.py
adaptiveagatepy/related_files.py
adaptiveagatepy/sample.py
adaptiveagatepy/sample_analyses.py
adaptiveagatepy-0.9.79.data/data/LICENSE.txt
adaptiveagatepy-0.9.79.dist-info/LICENSE.txt
adaptiveagatepy-0.9.79.dist-info/METADATA
adaptiveagatepy-0.9.79.dist-info/WHEEL
adaptiveagatepy-0.9.79.dist-info/top_level.txt
adaptiveagatepy-0.9.79.dist-info/RECORD
