Metadata-Version: 2.1
Name: adaptiveagatepy
Version: 0.9.79
Summary: Python APIs for accessing sequencing data in the Adaptive Biotechnologies Agate Datastore
Home-page: http://www.adaptiveagate.com
Author: Adaptive Biotechnologies Corporation
Author-email: agate-support@adaptivebiotech.com
License: UNKNOWN
Platform: UNKNOWN
Classifier: Programming Language :: Python :: 3
Classifier: Programming Language :: Python :: 3.6
Classifier: Programming Language :: Python :: 3.7
Classifier: Programming Language :: Python :: 3.8
Classifier: Programming Language :: Python :: 3.9
Classifier: Operating System :: OS Independent
Classifier: License :: OSI Approved :: GNU Lesser General Public License v3 (LGPLv3)
Requires-Dist: requests
Requires-Dist: pyodbc
Requires-Dist: msal
Requires-Dist: azure-storage-blob (>=12.8)
Requires-Dist: pyarrow
Requires-Dist: dask
Requires-Dist: dask[dataframe]
Requires-Dist: parameterized
